MANIFEST.in
README.txt
setup.py
docs/HISTORY.txt
docs/INSTALL.txt
docs/LICENSE.GPL
docs/LICENSE.txt
wildcard/__init__.py
wildcard.pdfpal.egg-info/PKG-INFO
wildcard.pdfpal.egg-info/SOURCES.txt
wildcard.pdfpal.egg-info/dependency_links.txt
wildcard.pdfpal.egg-info/entry_points.txt
wildcard.pdfpal.egg-info/namespace_packages.txt
wildcard.pdfpal.egg-info/not-zip-safe
wildcard.pdfpal.egg-info/requires.txt
wildcard.pdfpal.egg-info/top_level.txt
wildcard/pdfpal/__init__.py
wildcard/pdfpal/commandrunner.py
wildcard/pdfpal/commands.py
wildcard/pdfpal/configure.zcml
wildcard/pdfpal/events.py
wildcard/pdfpal/extender.py
wildcard/pdfpal/interfaces.py
wildcard/pdfpal/ocr.py
wildcard/pdfpal/settings.py
wildcard/pdfpal/setup.py
wildcard/pdfpal/thumbnail.py
wildcard/pdfpal/Extensions/Install.py
wildcard/pdfpal/browser/__init__.py
wildcard/pdfpal/browser/album-view.pt
wildcard/pdfpal/browser/async-monitor.pt
wildcard/pdfpal/browser/configure.zcml
wildcard/pdfpal/browser/thumbnails.py
wildcard/pdfpal/browser/views.py
wildcard/pdfpal/browser/files/application-pdf.png
wildcard/pdfpal/browser/files/colorbox/.DS_Store
wildcard/pdfpal/browser/files/colorbox/colorbox.css
wildcard/pdfpal/browser/files/colorbox/jquery.colorbox-min.js
wildcard/pdfpal/browser/files/colorbox/jquery.colorbox.js
wildcard/pdfpal/browser/files/colorbox/images/.DS_Store
wildcard/pdfpal/browser/files/colorbox/images/border.png
wildcard/pdfpal/browser/files/colorbox/images/controls.png
wildcard/pdfpal/browser/files/colorbox/images/loading.gif
wildcard/pdfpal/browser/files/colorbox/images/loading_background.png
wildcard/pdfpal/browser/files/colorbox/images/overlay.png
wildcard/pdfpal/browser/files/colorbox/images/internet_explorer/borderBottomCenter.png
wildcard/pdfpal/browser/files/colorbox/images/internet_explorer/borderBottomLeft.png
wildcard/pdfpal/browser/files/colorbox/images/internet_explorer/borderBottomRight.png
wildcard/pdfpal/browser/files/colorbox/images/internet_explorer/borderMiddleLeft.png
wildcard/pdfpal/browser/files/colorbox/images/internet_explorer/borderMiddleRight.png
wildcard/pdfpal/browser/files/colorbox/images/internet_explorer/borderTopCenter.png
wildcard/pdfpal/browser/files/colorbox/images/internet_explorer/borderTopLeft.png
wildcard/pdfpal/browser/files/colorbox/images/internet_explorer/borderTopRight.png
