Metadata-Version: 1.0
Name: wildcard.pdfpal
Version: 0.7b6
Summary: PDF Thumbnail generation, OCR indexing and extra views integrated with plone.app.async
Home-page: http://pypi.python.org/pypi/wildcard.pdfpal
Author: Nathan Van Gheem
Author-email: nathan.vangheem@wildcardcorp.com
License: GPL
Keywords: pdf plone thumbnail ocr async
Platform: UNKNOWN
Classifier: Framework :: Plone
Classifier: Programming Language :: Python
Classifier: Topic :: Software Development :: Libraries :: Python Modules
